maddaq/GTimer.py
maddaq/MadDAQData.py
maddaq/MadDAQModule.py
maddaq/Progress.py
maddaq/ScanManager.py
maddaq/__init__.py
maddaq/cmmds/__init__.py
maddaq/cmmds/analyze_data.py
maddaq/cmmds/file_info.py
maddaq/cmmds/fit_utils.py
maddaq/cmmds/getSpectrum.py
maddaq/cmmds/read_data.py
maddaq/cmmds/show_data.py
maddaq-0.7.15.dist-info/METADATA
maddaq-0.7.15.dist-info/WHEEL
maddaq-0.7.15.dist-info/entry_points.txt
maddaq-0.7.15.dist-info/top_level.txt
maddaq-0.7.15.dist-info/RECORD
